linto/__init__.py
linto/main.py
linto/models/__init__.py
linto/models/media.py
linto/services/__init__.py
linto/services/pollingService.py
linto/services/studioApiService.py
linto/tools/__init__.py
linto/tools/generate_service_config.py
linto/tools/remove_leading_slash.py
linto-1.1.2.dist-info/licenses/LICENSE
linto-1.1.2.dist-info/METADATA
linto-1.1.2.dist-info/WHEEL
linto-1.1.2.dist-info/top_level.txt
linto-1.1.2.dist-info/RECORD
