Metadata-Version: 2.4
Name: linto
Version: 1.1.2
Summary: Wrapper around LinTO Studio API
Author-email: Tom Darboux <tdarboux@linagora.com>
License-Expression: AGPL-3.0-or-later
Project-URL: Repository, https://github.com/linto-ai/linto-studio
Project-URL: Homepage, https://linto.ai
Keywords: STT,Whisper,Speech-to-Text,Transcript,Transcriber,Timestamps
Requires-Python: >=3.7
License-File: LICENSE
Requires-Dist: aiohttp
Dynamic: license-file
